Adder/adderCumSubtractor.v
module full_adder1b(
    input x, y, z,
    output sum, carry
);
    assign sum = x ^ y ^ z;
    assign carry = ((x & y) | (z & x) | (z & y));

endmodule

module adder_cum_subtractor4b (
    input [3:0]x, z,
    input cin,
    output [3:0] sum,
    output carry
);
    wire cout1, cout2, cout3;
    wire [3:0]y;
    // xor(y[0], z[0], cin);
    // xor(y[1], z[1], cin);
    // xor(y[2], z[2], cin);
    // xor(y[3], z[3], cin);
    assign y = {z[3] ^ cin, z[2] ^ cin, z[1] ^ cin, z[0] ^ cin};
    full_adder1b FA1 (x[0], y[0], cin, sum[0], cout1);
    full_adder1b FA2 (x[1], y[1], cout1, sum[1], cout2);
    full_adder1b FA3 (x[2], y[2], cout2, sum[2], cout3);
    full_adder1b FA4 (x[3], y[3], cout3, sum[3], carry);
endmodule

module tb_adder4b(
	output reg [3:0] bin1, bin2,
    output reg cin,
	input [3:0]sum,
    input carry
);
	initial begin
		$monitor("%t, When bin1=%b, bin2=%b cin=%b then Result is =%b , Carry =%b",$time,bin1,bin2,cin,sum,carry);
		   {bin1,bin2,cin} = 9'b010110101;
		#5 {bin1,bin2,cin} = 9'b001111101;
		#5 {bin1,bin2,cin} = 9'b111100110;
		#5 {bin1,bin2,cin} = 9'b011100011;
		#5 {bin1,bin2,cin} = 9'b000000011;
		#5 {bin1,bin2,cin} = 9'b111100000;
		#5 {bin1,bin2,cin} = 9'b011100011;
		#5 {bin1,bin2,cin} = 9'b011100010;
        #5 $finish;
	end
endmodule

module wb;
    wire [3:0] bin1, bin2, sum, bin3;
    wire cin, carry;
    initial begin
        $dumpfile("addersubtractor.vcd");
        $dumpvars(0, wb);
    end
    adder_cum_subtractor4b dut (bin1, bin2, cin, sum, carry);
    tb_adder4b tb (bin1, bin2, cin, sum, carry);
endmodule

build/addersubtractor.vcd
$date
	Fri May 17 09:22:28 2024
$end
$version
	Icarus Verilog
$end
$timescale
	1s
$end
$scope module wb $end
$var wire 4 ! sum [3:0] $end
$var wire 1 " cin $end
$var wire 1 # carry $end
$var wire 4 $ bin2 [3:0] $end
$var wire 4 % bin1 [3:0] $end
$scope module dut $end
$var wire 4 & z [3:0] $end
$var wire 4 ' y [3:0] $end
$var wire 4 ( x [3:0] $end
$var wire 4 ) sum [3:0] $end
$var wire 1 * cout3 $end
$var wire 1 + cout2 $end
$var wire 1 , cout1 $end
$var wire 1 " cin $end
$var wire 1 # carry $end
$scope module FA1 $end
$var wire 1 , carry $end
$var wire 1 - sum $end
$var wire 1 . x $end
$var wire 1 / y $end
$var wire 1 " z $end
$upscope $end
$scope module FA2 $end
$var wire 1 + carry $end
$var wire 1 0 sum $end
$var wire 1 1 x $end
$var wire 1 2 y $end
$var wire 1 , z $end
$upscope $end
$scope module FA3 $end
$var wire 1 * carry $end
$var wire 1 3 sum $end
$var wire 1 4 x $end
$var wire 1 5 y $end
$var wire 1 + z $end
$upscope $end
$scope module FA4 $end
$var wire 1 # carry $end
$var wire 1 6 sum $end
$var wire 1 7 x $end
$var wire 1 8 y $end
$var wire 1 * z $end
$upscope $end
$upscope $end
$scope module tb $end
$var wire 1 # carry $end
$var wire 4 9 sum [3:0] $end
$var reg 4 : bin1 [3:0] $end
$var reg 4 ; bin2 [3:0] $end
$var reg 1 " cin $end
$upscope $end
$upscope $end
$enddefinitions $end
$comment Show the parameter values. $end
$dumpall
$end
#0
$dumpvars
b1010 ;
b101 :
b1011 9
08
07
16
15
14
03
02
01
10
1/
1.
1-
1,
0+
1*
b1011 )
b101 (
b101 '
b1010 &
b101 %
b1010 $
0#
1"
b1011 !
$end
#5
06
0*
1+
13
b101 !
b101 )
b101 9
00
05
b1 '
04
11
b11 %
b11 (
b11 :
b1110 $
b1110 &
b1110 ;
#10
03
1,
1#
10
1*
1/
12
05
08
17
14
b10 !
b10 )
b10 9
0-
b11 '
b1111 %
b1111 (
b1111 :
b11 $
b11 &
b11 ;
0"
#15
10
13
0/
12
15
18
07
b110 !
b110 )
b110 9
0-
b1110 '
b111 %
b111 (
b111 :
b1 $
b1 &
b1 ;
1"
#20
0#
16
0*
0+
0,
13
10
b1111 !
b1111 )
b1111 9
1-
04
01
0.
b0 %
b0 (
b0 :
#25
0#
16
0*
13
0+
10
0,
0/
02
05
08
17
14
11
1.
b1111 !
b1111 )
b1111 9
1-
b0 '
b1111 %
b1111 (
b1111 :
b0 $
b0 &
b0 ;
0"
#30
1#
06
1+
1*
13
1,
0/
12
15
18
07
b110 !
b110 )
b110 9
0-
b1110 '
b111 %
b111 (
b111 :
b1 $
b1 &
b1 ;
1"
#35
1*
1+
00
03
16
0#
1,
1/
02
05
08
b1000 !
b1000 )
b1000 9
0-
b1 '
0"
